sellix/__init__.py
sellix/test.py
sellix/resources/__init__.py
sellix/resources/blacklist.py
sellix/resources/categories.py
sellix/resources/coupons.py
sellix/resources/customers.py
sellix/resources/feedback.py
sellix/resources/groups.py
sellix/resources/orders.py
sellix/resources/payments.py
sellix/resources/products.py
sellix/resources/queries.py
sellix/resources/subscriptions.py
sellix/resources/whitelists.py
sellix_python_sdk-1.0.9.1.dist-info/LICENSE
sellix_python_sdk-1.0.9.1.dist-info/METADATA
sellix_python_sdk-1.0.9.1.dist-info/WHEEL
sellix_python_sdk-1.0.9.1.dist-info/top_level.txt
sellix_python_sdk-1.0.9.1.dist-info/RECORD
