Metadata-Version: 2.1
Name: sellix-python-sdk
Version: 1.0.9.1
Home-page: https://github.com/Sellix/python-sdk
License-File: LICENSE
Requires-Dist: requests
